problema1/src/problema1.vhd
LIBRARY IEEE;
USE IEEE.STD_LOGIC_1164.ALL;

ENTITY problema1 IS
	PORT (
		A, B, C : IN std_logic;
		Z       : OUT std_logic
	);
END ENTITY problema1;

ARCHITECTURE logic OF problema1 IS

	SIGNAL D, E : std_logic;

BEGIN

	D <= A AND B;
	E <= A AND C;
	Z <= D OR E;

END ARCHITECTURE logic;

problema1/src/tb_problema1.vhd
LIBRARY ieee;
USE ieee.std_logic_1164.ALL;

ENTITY tb_problema1 IS
END tb_problema1;

ARCHITECTURE a OF tb_problema1 IS

	COMPONENT problema1 IS -- declaro componente de paridades.vhdl
		PORT (
			A, B, C : IN std_logic;
			Z       : OUT std_logic
		);
	END COMPONENT;

	SIGNAL InA, InB, InC : std_logic;
	SIGNAL salida        : std_logic;

BEGIN

	uut : problema1 PORT MAP(InA, InB, InC, salida); -- instancio paridades
	
	PROCESS
	BEGIN
		InA <= '0';
		InB <= '0';
		InC <= '0';
		WAIT FOR 10 ns;

		InA <= '0';
		InB <= '0';
		InC <= '1';
		WAIT FOR 10 ns;

		InA <= '0';
		InB <= '1';
		InC <= '0';
		WAIT FOR 10 ns;

		InA <= '0';
		InB <= '1';
		InC <= '1';
		WAIT FOR 10 ns;

		InA <= '1';
		InB <= '0';
		InC <= '0';
		WAIT FOR 10 ns;

		InA <= '1';
		InB <= '0';
		InC <= '1';
		WAIT FOR 10 ns;

		InA <= '1';
		InB <= '1';
		InC <= '0';
		WAIT FOR 10 ns;

		InA <= '1';
		InB <= '1';
		InC <= '1';
		WAIT FOR 10 ns;

	END PROCESS;
END a;

problema1/waves/tb_problema1.vcd
$date
  Mon May 13 16:07:37 2024
$end
$version
  GHDL v0
$end
$timescale
  1 fs
$end
$scope module standard $end
$upscope $end
$scope module textio $end
$upscope $end
$scope module std_logic_1164 $end
$upscope $end
$scope module tb_problema1 $end
$var reg 1 ! ina $end
$var reg 1 " inb $end
$var reg 1 # inc $end
$var reg 1 $ salida $end
$scope module uut $end
$var reg 1 % a $end
$var reg 1 & b $end
$var reg 1 ' c $end
$var reg 1 ( z $end
$var reg 1 ) d $end
$var reg 1 * e $end
$upscope $end
$upscope $end
$enddefinitions $end
#0
0!
0"
0#
0$
0%
0&
0'
0(
0)
0*
#10000000
1#
1'
#20000000
1"
0#
1&
0'
#30000000
1#
1'
#40000000
1!
0"
0#
1%
0&
0'
#50000000
1#
1$
1'
1(
1*
#60000000
1"
0#
1&
0'
1)
0*
#70000000
1#
1'
1*
#80000000
0!
0"
0#
0$
0%
0&
0'
0(
0)
0*
#90000000
1#
1'
#100000000
1"
0#
1&
0'
