problema3/src/problema3.vhd
library IEEE;
use IEEE.STD_LOGIC_1164.ALL;
use ieee.numeric_std.ALL;

entity problema3 is
    port(
        A,B,C,D   :in std_logic;
        display   :out std_logic_vector (6 downto 0)
    );
end entity problema3;

architecture arquitectura of problema3 is 
   
    signal aa,bb,cc,dd,votos  : integer := 0;
    signal aprobado     : std_logic_vector (6 downto 0) := "1110111";
    signal desaprobado  : std_logic_vector (6 downto 0) := "0111101";

begin

    with A select 
        aa <=   10 when '1',
                0  when others;
    with B select 
        bb <=   15 when '1',
                0  when others;
    with C select 
        cc <=   30 when '1',
                0  when others;
    with D select 
        dd <=   45 when '1',
                0  when others;
                
    process(aa, bb, cc, dd)
    begin
        display <= desaprobado;
        if (aa+bb+cc+dd) > 50 then
            display <= aprobado;
        end if; 
    end process;
             
end architecture arquitectura;

problema3/src/tb_problema3.vhd
library ieee;
use ieee.std_logic_1164.all;

entity tb_problema3 is
end tb_problema3;

architecture a of tb_problema3 is

	component problema3 is
		port(
			A,B,C,D   :in std_logic;
			display   :out std_logic_vector (6 downto 0)
		);
	end component problema3;

signal InA, InB, InC, InD : std_logic;
signal salida : std_logic_vector (6 downto 0);

begin

	uut: problema3  port map (InA, InB, InC, InD, salida); -- instancio paridades
	
	Process 
	begin
		
		InA <= '1';
		InB <= '0';
		InC <= '0';
		InD <= '1'; wait for 10 ns;
		
		InA <= '0';
		InB <= '1';
		InC <= '0';
		InD <= '1'; wait for 10 ns;

		InA <= '1';
		InB <= '1';
		InC <= '1';
		InD <= '0'; wait for 10 ns;
		
		InA <= '1';
		InB <= '1';
		InC <= '0';
		InD <= '0'; wait for 10 ns;
		
		InA <= '1';
		InB <= '0';
		InC <= '1';
		InD <= '0'; wait for 10 ns;

	End process;	
end a;

problema3/waves/tb_problema3.vcd
$date
  Mon May 13 20:58:38 2024
$end
$version
  GHDL v0
$end
$timescale
  1 fs
$end
$scope module standard $end
$upscope $end
$scope module textio $end
$upscope $end
$scope module std_logic_1164 $end
$upscope $end
$scope module numeric_std $end
$upscope $end
$scope module tb_problema3 $end
$var reg 1 ! ina $end
$var reg 1 " inb $end
$var reg 1 # inc $end
$var reg 1 $ ind $end
$var reg 7 % salida[6:0] $end
$scope module uut $end
$var reg 1 & a $end
$var reg 1 ' b $end
$var reg 1 ( c $end
$var reg 1 ) d $end
$var reg 7 * display[6:0] $end
$var integer 32 + aa $end
$var integer 32 , bb $end
$var integer 32 - cc $end
$var integer 32 . dd $end
$var integer 32 / votos $end
$var reg 7 0 aprobado[6:0] $end
$var reg 7 1 desaprobado[6:0] $end
$upscope $end
$upscope $end
$enddefinitions $end
#0
1!
0"
0#
1$
b1110111 %
1&
0'
0(
1)
b1110111 *
b1010 +
b0 ,
b0 -
b101101 .
b0 /
b1110111 0
b0111101 1
#10000000
0!
1"
0&
1'
b1110111 *
b0 +
b1111 ,
#20000000
1!
1#
0$
1&
1(
0)
b1110111 *
b1010 +
b11110 -
b0 .
#30000000
0#
b0111101 %
0(
b0111101 *
b0 -
#40000000
0"
1#
0'
1(
b0 ,
b11110 -
#50000000
0#
1$
b1110111 %
0(
1)
b1110111 *
b0 -
b101101 .
#60000000
0!
1"
0&
1'
b1110111 *
b0 +
b1111 ,
#70000000
1!
1#
0$
1&
1(
0)
b1110111 *
b1010 +
b11110 -
b0 .
#80000000
0#
b0111101 %
0(
b0111101 *
b0 -
#90000000
0"
1#
0'
1(
b0 ,
b11110 -
#100000000
0#
1$
b1110111 %
0(
1)
b1110111 *
b0 -
b101101 .
