problema2/src/conta.vhd
library ieee;
use ieee.std_logic_1164.all;
use ieee.numeric_std.all;

entity conta is
	generic	(
		MIN_COUNT : natural := 0;
		MAX_COUNT : natural := 256	);

	port	(
		clk		  : in std_logic;
		reset	  : in std_logic;
		enable	  : in std_logic;
		cout      : out std_logic;
		q		  : out integer range MIN_COUNT to MAX_COUNT	);
end entity;

architecture rtl of conta is
begin
	process (clk)
		variable   cnt: integer range MIN_COUNT to MAX_COUNT;
	begin
		if (rising_edge(clk)) then
			if reset = '1' then
				cnt := 0;
			elsif enable = '1' then cnt := cnt + 1;
				if cnt<= max_count/2 then cout<='0';
				else cout<='1';
				end iF;
				if cnt=MAX_COUNT then cnt:=0; end if;
			end if;
		end if;
		q <= cnt;
		--if cnt=MAX_COUNT then cnt:=0; end if;
	end process;
end rtl;

problema2/src/problema2.vhd
library IEEE;
use IEEE.STD_LOGIC_1164.ALL;
use ieee.numeric_std.all;

entity problema2 is
    port(
        clk_50Mhz, rst  :in std_logic;
        led       		:out std_logic
    );
end entity problema2;


architecture logic of problema2 is 

	component conta is
		generic	(
			MIN_COUNT : natural := 0;
			MAX_COUNT : natural := 256	);
	
		port	(
			clk		: in std_logic;
			reset	: in std_logic;
			enable	: in std_logic;
			cout	: out std_logic;
			q		: out integer range MIN_COUNT to MAX_COUNT);
	end component conta;
	
	signal clk_1hz : std_logic;

	begin
    cnt: conta generic map (0,10) -- 50_000_000 para 1 seg
        port map(clk_50Mhz, rst, '1', clk_1hz, open);
    
    led <= clk_1hz;
end architecture logic;

problema2/src/tb_problema2.vhd
library ieee;
use ieee.std_logic_1164.all;

entity tb_problema2 is
end tb_problema2;

architecture a of tb_problema2 is

	component problema2 is	  -- declaro componente de paridades.vhdl
		port(
			clk_50Mhz,rst  :in std_logic;
			led       :out std_logic
		);
	end component;

	signal clk, reset : std_logic;
	signal salida : std_logic;

	begin
		uut: problema2  port map (clk, reset, salida); -- instancio paridades
		
		Process 
			begin
			clk 	<= '1';
			reset 	<= '0'; wait for 10 ns;
			clk 	<= '0';
			reset 	<= '0'; wait for 10 ns;
		End process;	
end a;

problema2/waves/tb_problema2.vcd
$date
  Mon May 13 16:27:41 2024
$end
$version
  GHDL v0
$end
$timescale
  1 fs
$end
$scope module standard $end
$upscope $end
$scope module textio $end
$upscope $end
$scope module std_logic_1164 $end
$upscope $end
$scope module numeric_std $end
$upscope $end
$scope module tb_problema2 $end
$var reg 1 ! clk $end
$var reg 1 " reset $end
$var reg 1 # salida $end
$scope module uut $end
$var reg 1 $ clk_50mhz $end
$var reg 1 % rst $end
$var reg 1 & led $end
$var reg 1 ' clk_1hz $end
$scope module cnt $end
$var reg 1 ( clk $end
$var reg 1 ) reset $end
$var reg 1 * enable $end
$var reg 1 + cout $end
$var integer 32 , q $end
$upscope $end
$upscope $end
$upscope $end
$enddefinitions $end
#0
1!
0"
U#
1$
0%
U&
U'
1(
0)
1*
U+
b0 ,
#10000000
0!
0$
0(
#20000000
1!
0#
1$
0&
0'
1(
0+
b1 ,
#30000000
0!
0$
0(
#40000000
1!
1$
1(
b10 ,
#50000000
0!
0$
0(
#60000000
1!
1$
1(
b11 ,
#70000000
0!
0$
0(
#80000000
1!
1$
1(
b100 ,
#90000000
0!
0$
0(
#100000000
1!
1$
1(
b101 ,
#110000000
0!
0$
0(
#120000000
1!
1#
1$
1&
1'
1(
1+
b110 ,
#130000000
0!
0$
0(
#140000000
1!
1$
1(
b111 ,
#150000000
0!
0$
0(
#160000000
1!
1$
1(
b1000 ,
#170000000
0!
0$
0(
#180000000
1!
1$
1(
b1001 ,
#190000000
0!
0$
0(
#200000000
1!
1$
1(
b0 ,
#210000000
0!
0$
0(
#220000000
1!
0#
1$
0&
0'
1(
0+
b1 ,
#230000000
0!
0$
0(
#240000000
1!
1$
1(
b10 ,
#250000000
0!
0$
0(
#260000000
1!
1$
1(
b11 ,
#270000000
0!
0$
0(
#280000000
1!
1$
1(
b100 ,
#290000000
0!
0$
0(
#300000000
1!
1$
1(
b101 ,
#310000000
0!
0$
0(
#320000000
1!
1#
1$
1&
1'
1(
1+
b110 ,
#330000000
0!
0$
0(
#340000000
1!
1$
1(
b111 ,
#350000000
0!
0$
0(
#360000000
1!
1$
1(
b1000 ,
#370000000
0!
0$
0(
#380000000
1!
1$
1(
b1001 ,
#390000000
0!
0$
0(
#400000000
1!
1$
1(
b0 ,
#410000000
0!
0$
0(
#420000000
1!
0#
1$
0&
0'
1(
0+
b1 ,
#430000000
0!
0$
0(
#440000000
1!
1$
1(
b10 ,
#450000000
0!
0$
0(
#460000000
1!
1$
1(
b11 ,
#470000000
0!
0$
0(
#480000000
1!
1$
1(
b100 ,
#490000000
0!
0$
0(
#500000000
1!
1$
1(
b101 ,
#510000000
0!
0$
0(
#520000000
1!
1#
1$
1&
1'
1(
1+
b110 ,
#530000000
0!
0$
0(
#540000000
1!
1$
1(
b111 ,
#550000000
0!
0$
0(
#560000000
1!
1$
1(
b1000 ,
#570000000
0!
0$
0(
#580000000
1!
1$
1(
b1001 ,
#590000000
0!
0$
0(
#600000000
1!
1$
1(
b0 ,
#610000000
0!
0$
0(
#620000000
1!
0#
1$
0&
0'
1(
0+
b1 ,
#630000000
0!
0$
0(
#640000000
1!
1$
1(
b10 ,
#650000000
0!
0$
0(
#660000000
1!
1$
1(
b11 ,
#670000000
0!
0$
0(
#680000000
1!
1$
1(
b100 ,
#690000000
0!
0$
0(
#700000000
1!
1$
1(
b101 ,
#710000000
0!
0$
0(
#720000000
1!
1#
1$
1&
1'
1(
1+
b110 ,
#730000000
0!
0$
0(
#740000000
1!
1$
1(
b111 ,
#750000000
0!
0$
0(
#760000000
1!
1$
1(
b1000 ,
#770000000
0!
0$
0(
#780000000
1!
1$
1(
b1001 ,
#790000000
0!
0$
0(
#800000000
1!
1$
1(
b0 ,
#810000000
0!
0$
0(
#820000000
1!
0#
1$
0&
0'
1(
0+
b1 ,
#830000000
0!
0$
0(
#840000000
1!
1$
1(
b10 ,
#850000000
0!
0$
0(
#860000000
1!
1$
1(
b11 ,
#870000000
0!
0$
0(
#880000000
1!
1$
1(
b100 ,
#890000000
0!
0$
0(
#900000000
1!
1$
1(
b101 ,
#910000000
0!
0$
0(
#920000000
1!
1#
1$
1&
1'
1(
1+
b110 ,
#930000000
0!
0$
0(
#940000000
1!
1$
1(
b111 ,
#950000000
0!
0$
0(
#960000000
1!
1$
1(
b1000 ,
#970000000
0!
0$
0(
#980000000
1!
1$
1(
b1001 ,
#990000000
0!
0$
0(
#1000000000
1!
1$
1(
b0 ,
